LICENSE
MANIFEST.in
README.rst
setup.cfg
setup.py
admin_async_upload/__init__.py
admin_async_upload/fields.py
admin_async_upload/files.py
admin_async_upload/models.py
admin_async_upload/storage.py
admin_async_upload/urls.py
admin_async_upload/validators.py
admin_async_upload/views.py
admin_async_upload/widgets.py
admin_async_upload/static/admin_resumable/js/resumable.js
admin_async_upload/templates/admin_resumable/admin_file_input.html
admin_async_upload/templates/admin_resumable/user_file_input.html
django_async_upload.egg-info/PKG-INFO
django_async_upload.egg-info/SOURCES.txt
django_async_upload.egg-info/dependency_links.txt
django_async_upload.egg-info/requires.txt
django_async_upload.egg-info/top_level.txt
tests/test_uploads.py